libulb/__init__.py
libulb/tools.py
libulb/catalog/__init__.py
libulb/catalog/course.py
libulb/catalog/extractor.py
libulb/catalog/tree.yaml
libulb/gehol/__init__.py
libulb/gehol/courses.py
libulb/gehol/login.py
libulb/gehol/timetable.py
libulb/smileye_app/__init__.py
libulb/smileye_app/api.py
libulb/smileye_app/mesnotes.py
libulb/uv/poc.py
libulb-0.1.3.dist-info/DESCRIPTION.rst
libulb-0.1.3.dist-info/METADATA
libulb-0.1.3.dist-info/RECORD
libulb-0.1.3.dist-info/WHEEL
libulb-0.1.3.dist-info/entry_points.txt
libulb-0.1.3.dist-info/metadata.json
libulb-0.1.3.dist-info/top_level.txt
