Metadata-Version: 2.0
Name: libulb
Version: 0.1.3
Summary: Interact with ULB in python
Home-page: https://github.com/C4ptainCrunch/libulb
Author: Nikita Marchant
Author-email: nikita.marchant@ulb.ac.be
License: BSD
Platform: UNKNOWN
Classifier: Development Status :: 3 - Alpha
Classifier: Intended Audience :: Developers
Classifier: Topic :: Software Development :: Build Tools
Classifier: License :: OSI Approved :: BSD License
Classifier: Programming Language :: Python :: 3
Classifier: Programming Language :: Python :: 3.3
Classifier: Programming Language :: Python :: 3.4
Classifier: Programming Language :: Python :: 3.5
Requires-Dist: requests
Requires-Dist: BeautifulSoup4
Requires-Dist: six
Requires-Dist: PyYaml
Requires-Dist: html5lib
Requires-Dist: furl
